{
  "question": "How many weeks did it take me to watch all the Marvel Cinematic Universe movies and the main Star Wars films?",
  "question_date": "2023-05-30T18:41:00",
  "hypotheses": [
    {
      "query_anchor": "the user's duration to watch all MCU movies and main Star Wars films",
      "target_memory_types": [
        "episodic",
        "fact"
      ],
      "entities": [
        "Marvel Cinematic Universe",
        "Star Wars"
      ],
      "keywords": [
        "watch",
        "weeks",
        "MCU",
        "Star Wars"
      ],
      "time_constraint": {
        "operator": "on",
        "start": "",
        "end": "",
        "raw": ""
      },
      "locations": [],
      "state_keys": [
        "watch_duration_weeks"
      ],
      "relation_hints": [],
      "answer_dim": "content",
      "need_assistant_context": false,
      "need_multi_hop": false,
      "expected_evidence_count": 1,
      "missing_slots": [
        "start_date",
        "end_date"
      ],
      "confidence": 0.7
    }
  ]
}