[
  {
    "memory_id": "v1_0bd5d8e4194ba305b84b",
    "content": "User plans to rent a car in Italy, inspired by a good experience driving in California.",
    "dimension": {
      "memory_type": "profile",
      "time": {
        "event_start": "",
        "event_end": "",
        "valid_from": "",
        "valid_to": "",
        "precision": "unknown",
        "raw": ""
      },
      "locations": [
        "Italy"
      ],
      "reason": "",
      "purpose": "",
      "keywords": [
        "rent car",
        "Italy",
        "driving",
        "California"
      ],
      "entities": [],
      "topic": "",
      "relation": {
        "subject": "",
        "predicate": "",
        "object": ""
      },
      "state_key": "",
      "state_value": "",
      "state_status": "unknown",
      "preference": {
        "target": "",
        "polarity": "unknown",
        "strength": 0.0,
        "scope": "unknown"
      },
      "modality": "asserted"
    },
    "provenance": {
      "session_id": "0207968f_1",
      "session_index": 6,
      "source_ids": [
        40
      ],
      "source_uids": [
        "s0006u0004"
      ],
      "source_times": [
        "2023-04-26T15:22:02"
      ],
      "source_role": "user",
      "window_index": 3
    },
    "confidence": 0.9,
    "evidence_span": "I think I'll rent a car in Italy, especially since I had a good experience driving in California.",
    "assistant_replies": [
      "Excellent decision! Renting a car will give you the flexibility to explore Italy's countryside and scenic routes at your own pace.\n\n**Car Rental Companies:**\n\n1. **Avis**: A well-established company with a wide range of vehicles, including automatic transmission options.\n2. **Hertz**: Another popular choice with a large fleet of cars, including electric and hybrid options.\n3. **Europcar**: A European-based company with a wide selection of vehicles, including manual and automatic transmission options.\n4. **Sixt**: A German company with a strong presence in Italy, offering a variety of cars, including luxury and electric options.\n5. **Local companies**: Consider renting from local companies like **Autovia** or **Maggiore**, which might offer more competitive prices and a more personalized experience.\n\n**Types of Cars:**\n\n1. **Compact cars**: Ideal for navigating narrow Italian roads and parking in tight spaces. Models like Fiat Panda, Volkswagen Polo, or Ford Fiesta are popular choices.\n2. **Sedans**: A good option for comfort and fuel efficiency. Models like Toyota Corolla, Honda Civic, or Opel Astra are suitable for Italian roads.\n3. **Wagons**: If you need more space for luggage or passengers, consider a wagon like the Volkswagen Golf or Ford Focus.\n4. **Convertibles**: If you want to enjoy the Italian sun, consider a convertible like the Fiat 500C or Ford Mustang.\n\n**Tips:**\n\n1. **Manual transmission**: If you're comfortable with a stick shift, consider renting a manual transmission car, as it's often cheaper and more fuel-efficient.\n2. **Automatic transmission**: If you prefer an automatic, make sure to specify this when booking, as they might be less common in Italy.\n3. **Diesel engine**: Diesel cars are popular in Italy, and they can be more fuel-efficient, especially for long drives.\n4. **GPS and insurance**: Make sure to add a GPS system and insurance to your rental package, as they might not be included in the basic rate.\n5. **Parking and tolls**: Research parking options and toll roads in advance to avoid surprises.\n\n**Booking and Discounts:**\n\n1. **Book in advance**: Reserve your car well in advance to ensure availability and get the best rates.\n2. **Compare prices**: Use online travel agencies like Expedia, Kayak, or Skyscanner to compare prices and find deals.\n3. **Discount codes**: Look for discount codes or promotions on car rental company websites or through travel agencies.\n4. **Package deals**: Consider booking a package that includes car rental, accommodations, and flights for potential savings.\n\nNow that you're all set with car rental information, are you thinking of exploring any specific regions or towns in Italy, or do you have any questions about driving in Italy?"
    ]
  },
  {
    "memory_id": "v1_98f631d00cd0fe8a9fdf",
    "content": "User plans to focus on Tuscany and the Amalfi Coast for scenic drives, charming towns, and food.",
    "dimension": {
      "memory_type": "profile",
      "time": {
        "event_start": "",
        "event_end": "",
        "valid_from": "",
        "valid_to": "",
        "precision": "unknown",
        "raw": ""
      },
      "locations": [
        "Tuscany, Amalfi Coast"
      ],
      "reason": "",
      "purpose": "",
      "keywords": [
        "Tuscany",
        "Amalfi Coast",
        "scenic drives",
        "charming towns",
        "food"
      ],
      "entities": [],
      "topic": "",
      "relation": {
        "subject": "",
        "predicate": "",
        "object": ""
      },
      "state_key": "",
      "state_value": "",
      "state_status": "unknown",
      "preference": {
        "target": "",
        "polarity": "unknown",
        "strength": 0.0,
        "scope": "unknown"
      },
      "modality": "asserted"
    },
    "provenance": {
      "session_id": "0207968f_1",
      "session_index": 6,
      "source_ids": [
        41
      ],
      "source_uids": [
        "s0006u0005"
      ],
      "source_times": [
        "2023-04-26T15:22:02.500000"
      ],
      "source_role": "user",
      "window_index": 3
    },
    "confidence": 0.9,
    "evidence_span": "I think I'll focus on Tuscany and the Amalfi Coast, as they seem to offer a great combination of scenic drives, charming towns, and delicious food.",
    "assistant_replies": [
      "Tuscany and the Amalfi Coast are both incredible regions that offer a unique blend of natural beauty, history, and culture.\n\n**Tuscany:**\n\n1. **San Gimignano**: A medieval walled town famous for its towers and stunning views of the surrounding countryside.\n2. **Siena**: A charming hilltop town with a rich history, beautiful piazzas, and a famous cathedral.\n3. **Volterra**: A medieval town perched on a hill, known for its Etruscan ruins, stunning views, and alabaster workshops.\n4. **Chianti**: A region famous for its wine production, rolling hills, and picturesque villages like Greve in Chianti and Radda in Chianti.\n5. **Florence**: The capital city of Tuscany, known for its art, architecture, and history, including the Uffizi Gallery and Ponte Vecchio.\n\n**Amalfi Coast:**\n\n1. **Positano**: A colorful, picturesque town perched on the side of a hill, known for its beaches, boutique shopping, and vibrant nightlife.\n2. **Amalfi**: A historic town with a stunning cathedral, picturesque harbor, and a famous paper museum.\n3. **Ravello**: A charming town perched on top of the mountains, known for its stunning views, beautiful villas, and music festivals.\n4. **Sorrento**: A larger town with a beautiful old town, stunning views of the Bay of Naples, and a famous lemon liqueur.\n5. **Cinque Terre**: A string of five colorful towns on the Ligurian coast, connected by hiking trails and offering stunning ocean views.\n\n**Other towns and villages:**\n\n1. **Pienza**: A charming town in southern Tuscany, known for its pecorino cheese, beautiful views, and well-preserved medieval architecture.\n2. **Cortona**: A hilltop town in eastern Tuscany, known for its Etruscan ruins, beautiful views, and charming streets.\n3. **Maiori**: A charming town on the Amalfi Coast, known for its beautiful beach, stunning views, and historic center.\n4. **Atrani**: A picturesque town on the Amalfi Coast, known for its beautiful beach, stunning views, and charming streets.\n\nThese are just a few of the many towns and villages you can visit in Tuscany and the Amalfi Coast. Be sure to explore the countryside, visit local markets, and try the local cuisine to get a true taste of these regions.\n\nNow, are you planning to stay in one or two bases and explore the surrounding areas, or do you want to move around and stay in different towns and villages?"
    ]
  },
  {
    "memory_id": "v1_e5e21b9eb206d0efe46e",
    "content": "User plans to stay in Siena and then Positano or Amalfi for a few days each, exploring surrounding areas.",
    "dimension": {
      "memory_type": "profile",
      "time": {
        "event_start": "",
        "event_end": "",
        "valid_from": "",
        "valid_to": "",
        "precision": "unknown",
        "raw": ""
      },
      "locations": [
        "Siena, Positano, Amalfi"
      ],
      "reason": "",
      "purpose": "",
      "keywords": [
        "Siena",
        "Positano",
        "Amalfi",
        "stay",
        "explore"
      ],
      "entities": [],
      "topic": "",
      "relation": {
        "subject": "",
        "predicate": "",
        "object": ""
      },
      "state_key": "",
      "state_value": "",
      "state_status": "unknown",
      "preference": {
        "target": "",
        "polarity": "unknown",
        "strength": 0.0,
        "scope": "unknown"
      },
      "modality": "asserted"
    },
    "provenance": {
      "session_id": "0207968f_1",
      "session_index": 6,
      "source_ids": [
        42
      ],
      "source_uids": [
        "s0006u0006"
      ],
      "source_times": [
        "2023-04-26T15:22:03"
      ],
      "source_role": "user",
      "window_index": 3
    },
    "confidence": 0.9,
    "evidence_span": "I'm thinking of staying in Siena for a few days, and then heading to the Amalfi Coast and staying in Positano or Amalfi for a few days.",
    "assistant_replies": [
      "I think your plan is excellent! Staying in a few bases and exploring the surrounding areas is a great way to experience Italy's local culture, cuisine, and scenery without feeling rushed.\n\nSiena is a fantastic base for exploring Tuscany, and you'll have plenty of time to visit the surrounding hill towns, vineyards, and countryside. Positano or Amalfi are both great choices for the Amalfi Coast, and you'll be able to easily explore the other towns and villages along the coast, as well as take day trips to Pompeii and the Isle of Capri.\n\nHere are a few additional tips to consider:\n\n1. **Accommodation**: Book your accommodations in advance, especially during peak season. Consider staying in apartments or agriturismos, which can offer a more authentic experience and often have cooking facilities.\n2. **Transportation**: Research transportation options in advance, such as trains, buses, and ferries. Consider renting a car for a few days to explore the countryside, but be aware that parking can be challenging in some towns.\n3. **Day trips**: Plan your day trips in advance, including booking tickets and transportation. Consider hiring a guide or joining a tour group to get the most out of your visits.\n4. **Food and wine**: Be sure to try the local cuisine and wine, and consider taking a cooking class or wine tasting tour. Don't be afraid to try new things and ask for recommendations from locals.\n5. **Relaxation**: Remember to build in some relaxation time into your itinerary. Italy is a country that values la dolce vita (the sweet life), so be sure to take time to enjoy the scenery, people-watch, and soak up the atmosphere.\n\nOverall, your plan is well-thought-out, and I think you'll have a wonderful time exploring Italy. Buon viaggio!"
    ]
  },
  {
    "memory_id": "v1_fc47f049d3b17588ca41",
    "content": "User participated in a charity 5K run on October 16th and achieved a personal best time.",
    "dimension": {
      "memory_type": "episodic",
      "time": {
        "event_start": "2023-10-16",
        "event_end": "",
        "valid_from": "",
        "valid_to": "",
        "precision": "unknown",
        "raw": "2023-10-16"
      },
      "locations": [],
      "reason": "",
      "purpose": "charity",
      "keywords": [
        "charity 5K",
        "personal best",
        "October 16th"
      ],
      "entities": [],
      "topic": "",
      "relation": {
        "subject": "",
        "predicate": "",
        "object": ""
      },
      "state_key": "",
      "state_value": "",
      "state_status": "unknown",
      "preference": {
        "target": "",
        "polarity": "unknown",
        "strength": 0.0,
        "scope": "unknown"
      },
      "modality": "asserted"
    },
    "provenance": {
      "session_id": "b1d9eb66_4",
      "session_index": 7,
      "source_ids": [
        43
      ],
      "source_uids": [
        "s0007u0001"
      ],
      "source_times": [
        "2023-04-27T13:45:00.500000"
      ],
      "source_role": "user",
      "window_index": 3
    },
    "confidence": 0.95,
    "evidence_span": "I just participated in the charity 5K run on October 16th and got a personal best time",
    "assistant_replies": [
      "Congratulations on your personal best time in the charity 5K run! That's an amazing achievement, and it's great that you're feeling motivated to take on a new challenge.\n\nConsidering your recent success in a 5K, here are some fitness goal options you might consider:\n\n1. **10K or 10-mile race**: Take your running to the next level by increasing the distance. A 10K or 10-mile race is a natural progression from a 5K, and you can apply the training habits you've developed so far.\n2. **Half-marathon**: If you're feeling ambitious, you could aim to complete a half-marathon (13.1 miles). This will require more dedicated training, but it's a great way to challenge yourself and see significant progress.\n3. **Triathlon or duathlon**: If you enjoy running, you might consider adding swimming and cycling to your repertoire. A sprint triathlon or duathlon (run-bike-run) can be an exciting new challenge.\n4. **Strength training or weightlifting**: Focus on building overall strength and muscle mass. This can help improve your running performance and reduce your risk of injury. You could aim to complete a certain number of workouts per week or focus on specific exercises like squats, deadlifts, or bench press.\n5. **Obstacle course race (OCR)**: If you enjoy running and are looking for a fun, varied challenge, consider an obstacle course race like a Spartan Race or Tough Mudder. These events often involve running, crawling, climbing, and other physical challenges.\n6. **Cycling or swimming goal**: If you want to mix up your routine, consider setting a goal in cycling or swimming. You could aim to complete a certain number of miles or laps, or participate in a cycling or swimming event.\n7. **Trail running**: If you enjoy running on roads, you might want to try trail running. This can be a great way to mix up your routine and explore new outdoor environments.\n8. **Marathon training**: If you're feeling very ambitious, you could start training for a marathon (26.2 miles). This will require a significant time commitment, but it's an incredible achievement to strive for.\n9. **Fitness challenge**: Choose a specific fitness challenge, like doing 100 push-ups or squats per day, or completing a certain number of workouts per week. This can be a great way to stay motivated and focused.\n10. **Create your own goal**: Think about what motivates you and what you enjoy. You could set a goal to run a certain number of times per week, complete a certain number of workouts, or focus on nutrition and healthy eating.\n\nRemember to choose a goal that resonates with you and aligns with your interests and fitness level. It's essential to set a goal that's challenging yet achievable, so you can stay motivated and engaged throughout your journey.\n\nWhich of these options resonates with you, or do you have something else in mind?"
    ]
  },
  {
    "memory_id": "v1_8d39d7db3212a20082bc",
    "content": "User has been taking swimming lessons at the YMCA since September 1st.",
    "dimension": {
      "memory_type": "episodic",
      "time": {
        "event_start": "2023-09-01",
        "event_end": "",
        "valid_from": "",
        "valid_to": "",
        "precision": "unknown",
        "raw": "2023-09-01"
      },
      "locations": [
        "YMCA"
      ],
      "reason": "",
      "purpose": "learning to swim",
      "keywords": [
        "swimming lessons",
        "YMCA",
        "September 1st"
      ],
      "entities": [],
      "topic": "",
      "relation": {
        "subject": "",
        "predicate": "",
        "object": ""
      },
      "state_key": "",
      "state_value": "",
      "state_status": "unknown",
      "preference": {
        "target": "",
        "polarity": "unknown",
        "strength": 0.0,
        "scope": "unknown"
      },
      "modality": "asserted"
    },
    "provenance": {
      "session_id": "b1d9eb66_4",
      "session_index": 7,
      "source_ids": [
        44
      ],
      "source_uids": [
        "s0007u0002"
      ],
      "source_times": [
        "2023-04-27T13:45:01"
      ],
      "source_role": "user",
      "window_index": 3
    },
    "confidence": 0.95,
    "evidence_span": "I've been taking swimming lessons at the YMCA since September 1st",
    "assistant_replies": [
      "That's fantastic! Triathlons are an amazing way to challenge yourself and explore new skills. Considering your swimming lessons and running background, you're off to a great start!\n\nFor a beginner-friendly triathlon, I'd recommend looking for a sprint-distance triathlon, which typically consists of:\n\n* 750m swim (approximately 400-500 yards)\n* 12-15 mile bike ride\n* 3.1 mile run (a 5K)\n\nHere are some tips to help you find a suitable triathlon for your first event:\n\n1. **Look for a pool-based triathlon**: Since you're already comfortable with swimming in a pool, a pool-based triathlon will allow you to focus on transitioning between swim, bike, and run without worrying about open-water swimming.\n2. **Choose a flat bike course**: As a beginner, you'll want to focus on getting comfortable with the bike portion. A flat course will make it easier to manage your pace and conserve energy.\n3. **Opt for a smaller, local event**: Smaller events tend to be more low-key and less intimidating. They often have a more supportive atmosphere, which is perfect for your first triathlon.\n4. **Consider a women's-only or beginner-focused event**: Some triathlons cater specifically to women or beginners, offering additional support and guidance.\n\nHere are a few popular beginner-friendly triathlons in the United States:\n\n1. **Iron Girl Triathlon Series**: This series offers women's-only sprint-distance triathlons across the country, with a focus on beginner-friendly courses and supportive atmospheres.\n2. **Tri for a Cure**: This event series offers sprint-distance triathlons in various locations, with a focus on supporting cancer research and treatment.\n3. **USA Triathlon (USAT) Sprint Triathlons**: USAT offers a range of sprint-distance triathlons across the country, with a focus on providing a supportive environment for beginners.\n4. **Local YMCA or community triathlons**: Many YMCAs and community centers host their own triathlons, which can be a great way to stay close to home and get support from familiar faces.\n\nOnce you've found a few options, make sure to:\n\n* Check the event website for course details, registration information, and any specific rules or requirements.\n* Reach out to the event organizers or a local triathlon club for guidance and advice.\n* Start training specifically for the triathlon, focusing on brick workouts (back-to-back swim-bike or bike-run sessions) to prepare for the transitions.\n\nRemember, the most important thing is to have fun and enjoy the experience! You've already taken the first step by starting swimming lessons, and now it's time to take on the rest of the triathlon challenge!\n\nHow does that sound? Are you ready to start searching for your first triathlon?"
    ]
  },
  {
    "memory_id": "v1_ce6aede8c75f0f01d327",
    "content": "User is interested in a sprint-distance triathlon in the local area, possibly in spring.",
    "dimension": {
      "memory_type": "profile",
      "time": {
        "event_start": "spring",
        "event_end": "",
        "valid_from": "",
        "valid_to": "",
        "precision": "unknown",
        "raw": "spring"
      },
      "locations": [
        "local area"
      ],
      "reason": "",
      "purpose": "",
      "keywords": [
        "sprint-distance triathlon",
        "local area",
        "spring"
      ],
      "entities": [],
      "topic": "",
      "relation": {
        "subject": "",
        "predicate": "",
        "object": ""
      },
      "state_key": "",
      "state_value": "",
      "state_status": "unknown",
      "preference": {
        "target": "",
        "polarity": "unknown",
        "strength": 0.0,
        "scope": "unknown"
      },
      "modality": "asserted"
    },
    "provenance": {
      "session_id": "b1d9eb66_4",
      "session_index": 7,
      "source_ids": [
        45
      ],
      "source_uids": [
        "s0007u0003"
      ],
      "source_times": [
        "2023-04-27T13:45:01.500000"
      ],
      "source_role": "user",
      "window_index": 3
    },
    "confidence": 0.8,
    "evidence_span": "I think I'll look for a sprint-distance triathlon in my local area, maybe something in the spring.",
    "assistant_replies": [
      "Excellent decision! Learning to ride a bike is a crucial part of preparing for a triathlon, and it's great that you're thinking ahead.\n\nLearning to ride a bike as an adult can be a bit intimidating, but with some patience, practice, and guidance, you'll be pedaling like a pro in no time! Here are some tips to help you get started:\n\n1. **Get a bike that fits you**: Visit a local bike shop and ask for their help in finding a bike that's the right size for you. A hybrid or comfort bike with a flat handlebar is a great option for beginners.\n2. **Start in a safe area**: Find a flat, open space like a park, empty parking lot, or bike path where you can practice without worrying about traffic or obstacles.\n3. **Get comfortable with the bike**: Stand over the bike with your feet shoulder-width apart and grab the handlebars. Practice leaning the bike from side to side, front to back, and getting on and off.\n4. **Adjust the bike to fit you**: Make sure the saddle height is correct and the handlebars are at a comfortable height. This will help you maintain balance and control.\n5. **Practice balancing and gliding**: Start by sitting on the bike and gliding with your feet on the ground. Get comfortable with the feel of the bike and how it responds to your movements.\n6. **Add pedaling**: Once you're comfortable gliding, try pedaling. Start on a slight incline or a gentle slope to help you get started.\n7. **Practice, practice, practice**: The more you practice, the more comfortable you'll become. Start with short sessions and gradually increase your time and distance.\n8. **Consider taking a bike lesson or joining a beginner's bike group**: Many bike shops, community centers, or cycling clubs offer bike lessons or group rides specifically for beginners. This can be a great way to learn from experienced instructors and get feedback on your technique.\n9. **Focus on your body position**: Keep your weight centered over the bike, with your knees slightly bent and your back straight. This will help you maintain balance and control.\n10. **Don't be too hard on yourself**: Learning to ride a bike takes time and patience. Don't worry if you don't pick it up right away. You'll get there with practice and persistence!\n\nAdditionally, here are a few triathlon-specific bike tips:\n\n* **Get comfortable with clipping in and out of pedals**: You'll need to be able to quickly clip in and out of your pedals during transitions, so practice this skill regularly.\n* **Practice riding with your triathlon gear**: Get used to riding with your water bottle, bike computer, and any other gear you plan to use during the triathlon.\n* **Focus on your bike handling skills**: Practice cornering, braking, and accelerating to build your confidence and control on the bike.\n\nRemember, the key to learning to ride a bike is to be consistent and patient. Start with short sessions and gradually build up your endurance and skills. You'll be ready to tackle that sprint-distance triathlon in no time!\n\nHow do you feel about getting started with learning to ride a bike? Do you have any specific concerns or questions about the process?"
    ]
  },
  {
    "memory_id": "v1_e96deb18e9b3613deafb",
    "content": "User is concerned about falling off the bike but will wear a helmet and follow safety precautions.",
    "dimension": {
      "memory_type": "profile",
      "time": {
        "event_start": "",
        "event_end": "",
        "valid_from": "",
        "valid_to": "",
        "precision": "unknown",
        "raw": ""
      },
      "locations": [],
      "reason": "",
      "purpose": "",
      "keywords": [
        "falling off bike",
        "helmet",
        "safety precautions"
      ],
      "entities": [],
      "topic": "",
      "relation": {
        "subject": "",
        "predicate": "",
        "object": ""
      },
      "state_key": "",
      "state_value": "",
      "state_status": "unknown",
      "preference": {
        "target": "",
        "polarity": "unknown",
        "strength": 0.0,
        "scope": "unknown"
      },
      "modality": "asserted"
    },
    "provenance": {
      "session_id": "b1d9eb66_4",
      "session_index": 7,
      "source_ids": [
        46
      ],
      "source_uids": [
        "s0007u0004"
      ],
      "source_times": [
        "2023-04-27T13:45:02"
      ],
      "source_role": "user",
      "window_index": 3
    },
    "confidence": 0.8,
    "evidence_span": "I'm a bit concerned about falling off the bike, but I know that's a normal part of the learning process. I'll make sure to wear a helmet and follow all the safety precautions.",
    "assistant_replies": [
      "That's the right attitude! Falling off the bike is a normal part of the learning process, and it's great that you're aware of the importance of safety precautions.\n\nWearing a helmet is an absolute must, and you should also consider the following accessories to make your ride more comfortable and efficient:\n\n1. **Cycling shorts**: These padded shorts can help reduce discomfort and chafing in the saddle area. They're a game-changer for longer rides!\n2. **Gloves**: Cycling gloves provide grip, protection, and comfort for your hands. They can also help with control and braking.\n3. **Comfort saddle**: If you find the saddle uncomfortable, consider investing in a comfort saddle or a saddle with a cutout to reduce pressure on sensitive areas.\n4. **Water bottle and cage**: Stay hydrated during your rides with a water bottle and cage attached to your bike.\n5. **Pedals with toe clips or clipless pedals**: These can help you generate more power and efficiency while pedaling.\n6. **Cycling shoes**: If you plan to ride regularly, consider investing in cycling shoes with stiff soles to improve pedaling efficiency.\n7. **Mirror or rearview device**: A mirror or rearview device can help you stay aware of your surroundings and potential hazards behind you.\n8. **Basic tool kit and pump**: Carry a basic tool kit with you, including a pump, tire levers, and Allen wrenches, in case you need to make minor adjustments or repairs on the go.\n9. **Reflective gear and lights**: If you plan to ride in low-light conditions, consider adding reflective gear and lights to increase your visibility.\n10. **Bike computer or GPS device**: A bike computer or GPS device can help you track your distance, speed, and other metrics, which can be motivating and helpful for training.\n\nRemember, you don't need to buy all of these accessories at once. Start with the essentials and add more as you become more comfortable with your bike and riding style.\n\nAs you begin learning to ride, keep the following tips in mind:\n\n* **Start on a flat surface**: Find a flat, open area like a park or empty parking lot to practice your riding skills.\n* **Get comfortable with the controls**: Practice using the brakes, gears (if your bike has them), and pedals before heading out on a ride.\n* **Look where you want to go**: Keep your eyes on the horizon or the path ahead, and avoid staring at the ground or obstacles.\n* **Relax and have fun**: Remember to relax and enjoy the ride! The more you tense up, the more likely you are to lose control or fall.\n\nYou got this! You're taking the first step towards becoming a triathlete, and that's something to be proud of. Keep me updated on your progress, and don't hesitate to ask if you have any more questions or concerns!"
    ]
  },
  {
    "memory_id": "v1_a9d330ead613f063c4c0",
    "content": "User is considering getting a triathlon bike for performance improvement.",
    "dimension": {
      "memory_type": "profile",
      "time": {
        "event_start": "",
        "event_end": "",
        "valid_from": "",
        "valid_to": "",
        "precision": "unknown",
        "raw": ""
      },
      "locations": [],
      "reason": "",
      "purpose": "",
      "keywords": [
        "triathlon bike",
        "performance",
        "investment"
      ],
      "entities": [],
      "topic": "",
      "relation": {
        "subject": "",
        "predicate": "",
        "object": ""
      },
      "state_key": "",
      "state_value": "",
      "state_status": "unknown",
      "preference": {
        "target": "",
        "polarity": "unknown",
        "strength": 0.0,
        "scope": "unknown"
      },
      "modality": "asserted"
    },
    "provenance": {
      "session_id": "b1d9eb66_4",
      "session_index": 7,
      "source_ids": [
        47
      ],
      "source_uids": [
        "s0007u0005"
      ],
      "source_times": [
        "2023-04-27T13:45:02.500000"
      ],
      "source_role": "user",
      "window_index": 3
    },
    "confidence": 0.8,
    "evidence_span": "I'm thinking about getting a triathlon bike. I've heard they're designed specifically for triathletes and can make a big difference in my performance.",
    "assistant_replies": [
      "As a triathlete, a triathlon bike can be a valuable investment, but it's essential to consider your current level, goals, and budget before making a decision.\n\nTriathlon bikes, also known as time trial (TT) bikes, are designed specifically for triathletes and offer several advantages:\n\n1. **Aerodynamics**: Triathlon bikes are designed to reduce air resistance, which can save you time and energy during the bike leg.\n2. **Comfort**: They often feature a more aggressive riding position, which can help you maintain a strong aerodynamic position and reduce fatigue.\n3. **Integration**: Many triathlon bikes come with integrated components, such as hidden brakes, internal cable routing, and aerodynamic wheels, which can further reduce air resistance.\n4. **Specificity**: Triathlon bikes are designed for the unique demands of triathlon, with features like a steeper seat tube angle and a shorter top tube, which can help you maintain a comfortable position during the bike leg.\n\nHowever, there are some points to consider before investing in a triathlon bike:\n\n1. **Cost**: Triathlon bikes are typically more expensive than road bikes or hybrid bikes, with prices ranging from $2,000 to $10,000 or more.\n2. **Fit**: Triathlon bikes have a more aggressive riding position, which can be uncomfortable for some riders, especially those with back or neck issues.\n3. **Limited versatility**: Triathlon bikes are designed specifically for triathlon and time trialing, so they might not be the best choice for casual riding or other types of cycling.\n\nIf you're a beginner or intermediate triathlete, a road bike or hybrid bike can still be a great option. They can provide a more comfortable riding position and are often more versatile, allowing you to ride on various terrain and in different conditions.\n\nHere are some questions to ask yourself before deciding:\n\n1. **What's your current level of experience and fitness?** If you're a beginner, you might not need a triathlon bike just yet.\n2. **What's your budget?** If you're on a tight budget, a road bike or hybrid bike might be a more affordable option.\n3. **What are your goals?** If you're aiming to compete at a high level or want to optimize your performance, a triathlon bike might be worth considering.\n4. **Do you have access to a professional bike fitter?** A good bike fitter can help you optimize your position on a road bike or hybrid bike, making it more comfortable and efficient.\n\nIf you do decide to invest in a triathlon bike, make sure to:\n\n1. **Test ride several models**: Try out different triathlon bikes to find the one that fits you best.\n2. **Work with a professional bike fitter**: Get a professional bike fit to ensure you're in an optimal position on the bike.\n3. **Consider renting or demoing a triathlon bike**: Many bike shops offer rental or demo options, which can give you a chance to try out a triathlon bike before committing to a purchase.\n\nUltimately, the decision to invest in a triathlon bike depends on your individual circumstances, goals, and budget. If you're unsure, consider consulting with a coach, bike fitter, or experienced triathlete to help you make an informed decision."
    ]
  }
]