{
  "question": "How many doctor's appointments did I go to in March?",
  "question_date": "2023-03-27T23:35:00",
  "hypotheses": [
    {
      "query_anchor": "the user's doctor appointments in March 2023",
      "target_memory_types": [
        "episodic"
      ],
      "entities": [
        "doctor appointment"
      ],
      "keywords": [
        "doctor appointment",
        "March"
      ],
      "time_constraint": {
        "operator": "between",
        "start": "2023-03-01T00:00:00",
        "end": "2023-03-31T23:59:59",
        "raw": "in March"
      },
      "locations": [],
      "state_keys": [],
      "relation_hints": [],
      "answer_dim": "content",
      "need_assistant_context": false,
      "need_multi_hop": false,
      "expected_evidence_count": 1,
      "missing_slots": [],
      "confidence": 0.9
    }
  ]
}