{
  "s0036u0006": {
    "source_uid": "s0036u0006",
    "source_id": 181,
    "window_source_id": 1,
    "session_id": "0159547c_1",
    "session_index": 36,
    "session_local_user_index": 6,
    "timestamp": "2023-05-21T07:34:03",
    "assistant_reply": "That's wonderful to hear! It's great that Luna took to the new litter box so easily, and it's even better that it's made a big difference for you too!\n\nIt's amazing how much of a game-changer a simple thing like an automated litter box can be, isn't it? The convenience, the reduced smell, the extra time you get back in your day... it all adds up to a big win!\n\nAnd I love that you're using the extra time to focus on brushing Luna more frequently! She's one lucky kitty to have such a dedicated and caring owner like you.\n\nBy the way, have you noticed any other benefits to the automated litter box, like reduced litter tracking or less mess around the house?"
  },
  "s0037u0001": {
    "source_uid": "s0037u0001",
    "source_id": 182,
    "window_source_id": 2,
    "session_id": "41d20601",
    "session_index": 37,
    "session_local_user_index": 1,
    "timestamp": "2023-05-21T23:47:00.500000",
    "assistant_reply": "Flea and tick prevention is essential for your kitty's comfort and health! There are many great options available, and I'd be happy to help you find the right one for Luna. Here are some popular flea and tick prevention medications for cats:\n\n**Topical Treatments:**\n\n1. **Frontline Plus**: A popular and effective option that kills fleas, ticks, and chewing lice. It's applied directly to the skin between the shoulder blades.\n2. **Advantage II**: Similar to Frontline, it kills fleas, ticks, and chewing lice, and also contains an insect growth regulator to prevent flea eggs from hatching.\n3. **Revolution**: A broad-spectrum medication that not only kills fleas and ticks but also prevents heartworms and treats ear mites and roundworms.\n\n**Oral Medications:**\n\n1. **Capstar**: A fast-acting tablet that kills adult fleas and starts working within 30 minutes. It's often used in conjunction with a topical treatment.\n2. **Comfortis**: A chewable tablet that kills fleas and prevents infestations for a month.\n3. **Trifexis**: A combination medication that prevents fleas, ticks, heartworms, and intestinal parasites.\n\n**Collars:**\n\n1. **Seresto**: A popular flea and tick collar that provides 8 months of protection against fleas and ticks, as well as repellency against biting flies and mosquitoes.\n2. **Scalibor**: A collar that kills fleas, ticks, and biting lice, and also repels sand flies and mosquitoes.\n\n**Natural and Alternative Options:**\n\n1. **Natural Flea & Tick Shampoos**: Medicated shampoos containing ingredients like pyrethrin, neem oil, or tea tree oil can help control fleas and ticks.\n2. **Diatomaceous Earth**: A natural, non-toxic powder that can be used to repel and kill fleas and ticks.\n\nBefore choosing a flea and tick prevention medication, consider the following factors:\n\n* Luna's age, weight, and health status\n* The severity of the flea and tick infestation\n* Any allergies or sensitivities your cat may have\n* Your personal preferences (e.g., topical vs. oral, natural vs. conventional)\n\nIt's always best to consult with your veterinarian to determine the most effective and safe option for Luna. They can help you choose a product that meets your cat's specific needs and health status."
  },
  "s0037u0002": {
    "source_uid": "s0037u0002",
    "source_id": 183,
    "window_source_id": 3,
    "session_id": "41d20601",
    "session_index": 37,
    "session_local_user_index": 2,
    "timestamp": "2023-05-21T23:47:01",
    "assistant_reply": "Finding the right flea and tick prevention medication for Max is crucial for his comfort and health. There are many great options available, and I'd be happy to help you explore them. Here are some popular flea and tick prevention medications for dogs:\n\n**Topical Treatments:**\n\n1. **Frontline Gold**: A popular and effective option that kills fleas, ticks, and chewing lice. It's applied directly to the skin between the shoulder blades.\n2. **Advantix II**: Similar to Frontline, it kills fleas, ticks, and chewing lice, and also repels biting flies and mosquitoes.\n3. **K9 Advantix**: A topical treatment that kills fleas, ticks, and chewing lice, and also repels biting flies, mosquitoes, and sand flies.\n4. **Activyl**: A fast-acting topical treatment that kills fleas and ticks, and also contains an insect growth regulator to prevent flea eggs from hatching.\n\n**Oral Medications:**\n\n1. **Nexgard**: A popular chewable tablet that kills fleas and ticks, and also prevents flea infestations for a month.\n2. **Comfortis**: A fast-acting chewable tablet that kills fleas and prevents infestations for a month.\n3. **Trifexis**: A combination medication that prevents fleas, ticks, heartworms, and intestinal parasites.\n4. **Capstar**: A fast-acting tablet that kills adult fleas and starts working within 30 minutes.\n\n**Collars:**\n\n1. **Seresto**: A popular flea and tick collar that provides 8 months of protection against fleas and ticks, as well as repellency against biting flies and mosquitoes.\n2. **Scalibor**: A collar that kills fleas, ticks, and biting lice, and also repels sand flies and mosquitoes.\n\n**Shampoos and Sprays:**\n\n1. **Medicated Shampoos**: Shampoos containing ingredients like pyrethrin, permethrin, or fipronil can help kill fleas and ticks on contact.\n2. **Flea and Tick Sprays**: Sprays containing ingredients like pyrethrin, permethrin, or fipronil can be used to kill fleas and ticks on dogs, as well as in their environment.\n\n**Natural and Alternative Options:**\n\n1. **Natural Flea and Tick Shampoos**: Medicated shampoos containing ingredients like neem oil, tea tree oil, or eucalyptus oil can help control fleas and ticks.\n2. **Diatomaceous Earth**: A natural, non-toxic powder that can be used to repel and kill fleas and ticks.\n\nBefore choosing a flea and tick prevention medication for Max, consider the following factors:\n\n* Max's age, weight, and health status\n* The severity of the flea and tick infestation\n* Any allergies or sensitivities your dog may have\n* Your personal preferences (e.g., topical vs. oral, natural vs. conventional)\n\nIt's always best to consult with your veterinarian to determine the most effective and safe option for Max. They can help you choose a product that meets your dog's specific needs and health status."
  },
  "s0037u0003": {
    "source_uid": "s0037u0003",
    "source_id": 184,
    "window_source_id": 4,
    "session_id": "41d20601",
    "session_index": 37,
    "session_local_user_index": 3,
    "timestamp": "2023-05-21T23:47:01.500000",
    "assistant_reply": "Sensitive skin can be a challenge! Finding the right shampoo for Max's sensitive skin is crucial to keep him comfortable and happy. Here are some gentle and effective shampoo recommendations for dogs with sensitive skin:\n\n**Hypoallergenic Shampoos:**\n\n1. **Oatmeal Shampoos**: Oatmeal is a natural soothing agent that calms and moisturizes the skin. Look for shampoos containing colloidal oatmeal, such as:\n\t* Earthbath All-Natural Oatmeal & Aloe Shampoo\n\t* Nature's Specialties Oatmeal Dog Shampoo\n2. **Aloe Vera Shampoos**: Aloe vera is known for its anti-inflammatory and soothing properties, making it perfect for sensitive skin:\n\t* Aloe vera Shampoo by Nature's Gate\n\t* Aloe Vera Dog Shampoo by Earthbath\n3. **Sensitive Skin Formulas**: Shampoos specifically designed for sensitive skin, often containing gentle ingredients like:\n\t* Hydrocortisone: reduces inflammation and itching\n\t* Chamomile: calms and soothes the skin\n\t* Green tea: antioxidant and anti-inflammatory properties\n\nSome great options include:\n\n\t* Epi-Soothe Sensitive Skin Shampoo by Virbac\n\t* Sensitive Skin Shampoo by Douxo\n\t* Gentle Skin Shampoo by Royal Canin\n\n**Natural and Organic Options:**\n\n1. **Coconut Oil Shampoos**: Coconut oil is a natural moisturizer and anti-inflammatory agent:\n\t* Coconut Oil Dog Shampoo by Nature's Gate\n\t* Coconut Oil Shampoo by Earthbath\n2. **Shikakai Shampoos**: Shikakai is a natural ingredient that cleanses and soothes the skin:\n\t* Shikakai Dog Shampoo by Nature's Gate\n\t* Shikakai Shampoo by Earthbath\n\n**Tips and Reminders:**\n\n* Always read the ingredient list and look for certifications like hypoallergenic, sensitive skin, or natural/organic.\n* Patch test a small area of Max's skin before using a new shampoo to ensure he doesn't have any adverse reactions.\n* Avoid shampoos containing harsh chemicals, dyes, or fragrances, which can exacerbate sensitive skin.\n* Consult with your veterinarian for personalized recommendations, especially if Max has a skin condition or allergy.\n\nRemember, every dog's skin is different, so it might take some trial and error to find the perfect shampoo for Max. Be patient, and with a little persistence, you'll find a shampoo that makes him feel comfortable and happy!"
  },
  "s0037u0004": {
    "source_uid": "s0037u0004",
    "source_id": 185,
    "window_source_id": 5,
    "session_id": "41d20601",
    "session_index": 37,
    "session_local_user_index": 4,
    "timestamp": "2023-05-21T23:47:02",
    "assistant_reply": "Pet supplies can quickly take over a space, can't they? Don't worry, I've got some purr-fectly helpful tips to get your laundry room cabinet organized and clutter-free!\n\n**1. Purge and Categorize:**\n Begin by taking everything out of the cabinet and sorting items into categories, such as:\n\t* Food and treats\n\t* Toys and chews\n\t* Grooming supplies (shampoos, brushes, etc.)\n\t* Medications and supplements\n\t* Flea and tick prevention\n\t* Miscellaneous (collars, leashes, etc.)\n\n**2. Assign a Home:**\n Once you've categorized your supplies, assign a specific shelf or section of the cabinet to each group. This will help maintain organization and make it easier to find what you need.\n\n**3. Use Storage Containers:**\n Utilize bins, baskets, or containers to store small items like toys, treats, or grooming supplies. Label each container so you can easily identify what's inside.\n\n**4. Maximize Vertical Space:**\n Make the most of your cabinet's vertical space by using stackable shelves or baskets. This will help keep items off the floor and prevent clutter from building up.\n\n**5. Keep Frequently Used Items Accessible:**\n Store frequently used items in easy-to-reach locations, such as the top shelf or in a convenient basket near the front of the cabinet.\n\n**6. Label and Sign:**\n Label each shelf or section with its contents, and consider adding a sign to the cabinet door indicating what's stored inside. This will help you and others quickly find what they need.\n\n**7. Keep it Clean:**\n Set aside some time each month to tidy up the cabinet and remove any expired or unused items. This will prevent clutter from building up again.\n\n**Additional Tips:**\n\n* Consider using a turntable or lazy Susan to make it easy to access items in the back of the cabinet.\n* Store heavy items, like pet food, on the bottom shelf to prevent them from falling and causing a mess.\n* Keep a donation bin or bag in the cabinet to collect items you no longer need or use, and donate them to a local animal shelter or pet rescue organization.\n\nBy following these tips, you'll be able to create a more organized, clutter-free space that makes it easy to find what you need for Max and Luna. Happy organizing!"
  },
  "s0037u0005": {
    "source_uid": "s0037u0005",
    "source_id": 186,
    "window_source_id": 6,
    "session_id": "41d20601",
    "session_index": 37,
    "session_local_user_index": 5,
    "timestamp": "2023-05-21T23:47:02.500000",
    "assistant_reply": "Rabbit toys! I'd be delighted to help you find a new toy for Benny! Rabbits need plenty of stimulation and exercise to stay happy and healthy, and toys play a crucial role in their enrichment. Here are some safe and durable toy recommendations for Benny:\n\n**Chewing Toys:**\n\n1. **Untreated Wood Toys**: Rabbits love to chew, and untreated wood toys are perfect for satisfying this instinct. Look for wooden toys made from safe woods like apple, willow, or birch.\n2. **Hay Balls**: Hay balls are a great way to provide Benny with a fun and healthy snack while keeping him occupied.\n3. **Cardboard Rolls**: Toilet paper or paper towel rolls are perfect for rabbits to chew on and destroy (in a good way!).\n\n**Interactive Toys:**\n\n1. **Tunnels and Tents**: Rabbits love to hide, play, and explore, making tunnels and tents an excellent choice.\n2. **Food Puzzle Toys**: Challenge Benny's problem-solving skills with food puzzle toys that dispense treats as he plays.\n3. **Bell Toys**: Rabbits love to play with noisy toys, and bell toys are a great way to encourage exercise and entertainment.\n\n**Safe Materials:**\n\n1. **Recycled Paper Products**: Paper-based toys, like paper bags or cardboard boxes, are safe and eco-friendly.\n2. **Natural Fibers**: Toys made from natural fibers like cotton, hemp, or sisal are great for rabbits to chew on.\n3. **Non-Toxic Plastics**: Look for toys made from non-toxic, BPA-free plastics that won't harm Benny if ingested.\n\n**Avoid:**\n\n1. **Toys with Small Parts**: Avoid toys with small parts that can be easily detached and ingested, like eyes, noses, or small beads.\n2. **Toys with Strings or Yarn**: Rabbits can easily get tangled or ingest strings or yarn, so it's best to avoid toys with these materials.\n3. **Toys with Toxic Materials**: Never give Benny toys made from toxic materials like lead, zinc, or PVC.\n\nSome great brands for rabbit toys include:\n\n* Kaytee\n* Oxbow\n* Pet Zone\n* Small Pet Select\n* Ware Manufacturing\n\nRemember to rotate Benny's toys regularly to keep him engaged and interested. You can also try hiding treats or hay inside toys to encourage foraging behavior. Happy shopping for Benny's new toy!"
  },
  "s0037u0006": {
    "source_uid": "s0037u0006",
    "source_id": 187,
    "window_source_id": 7,
    "session_id": "41d20601",
    "session_index": 37,
    "session_local_user_index": 6,
    "timestamp": "2023-05-21T23:47:03",
    "assistant_reply": "Hiding places for Benny! Rabbits need plenty of hiding spots to feel secure and comfortable in their environment. Hiding places can help reduce stress and provide a sense of safety, so it's great that you're considering getting Benny some new hideaways! Here are some recommendations:\n\n**Types of Hiding Places:**\n\n1. **Tunnels and Tents**: Rabbits love to burrow and hide in tunnels and tents. Look for ones made from durable materials like canvas or polyester.\n2. **Boxes and Crates**: Cardboard boxes or wooden crates can make great hiding places for Benny. You can even cut holes in them to create tunnels and make them more interesting.\n3. **Huts and Houses**: Rabbit huts and houses provide a cozy, enclosed space for Benny to hide and feel secure.\n4. **Caves and Dens**: If you have a larger rabbit enclosure or a rabbit-proofed room, consider adding a cave or den for Benny to hide in.\n\n**Features to Look For:**\n\n1. **Sturdy Construction**: Make sure the hiding place is sturdy and won't collapse or tip over if Benny jumps on it or tries to move it.\n2. **Easy to Clean**: Choose hiding places with easy-to-clean surfaces or removable parts to make maintenance a breeze.\n3. **Ventilation**: Ensure the hiding place has good ventilation to prevent moisture buildup and keep Benny healthy.\n4. **Multiple Entrances and Exits**: Hiding places with multiple entrances and exits can help Benny feel more secure and provide exercise opportunities.\n\n**Some Great Options:**\n\n1. **Kaytee Rabbit Hideaway**: A cozy, easy-to-clean hideaway with a removable roof for easy access.\n2. **Oxbow Rabbit Hut**: A sturdy, ventilated hut with a sloping roof to prevent water accumulation.\n3. **Ware Manufacturing Rabbit Tunnel**: A durable, collapsible tunnel with multiple entrances and exits.\n\n**Tips and Reminders:**\n\n1. **Introduce New Hiding Places Gradually**: Add new hiding places gradually to prevent overwhelming Benny and give him time to get used to them.\n2. **Provide Multiple Hiding Places**: Offer multiple hiding places to give Benny choices and reduce competition for resources.\n3. **Clean Hiding Places Regularly**: Regularly clean and disinfect hiding places to keep Benny healthy and prevent the spread of disease.\n\nI hope this helps you find the perfect hiding places for Benny!"
  },
  "s0038u0001": {
    "source_uid": "s0038u0001",
    "source_id": 188,
    "window_source_id": 8,
    "session_id": "sharegpt_xLjgprT_0",
    "session_index": 38,
    "session_local_user_index": 1,
    "timestamp": "2023-05-21T22:56:00.500000",
    "assistant_reply": "Sure! Here's a story I came up with about perseverance:\n\nThere was once a young dragon named Ember who lived in a great, sprawling cave system with his family. Ember was a scrappy little dragon, always eager to explore and discover new things. But as much as he loved adventure, he had one major flaw: he was extremely stubborn.\n\nOne day, while out exploring, Ember stumbled upon a beautiful, glittering gemstone. It was the most gorgeous thing he had ever seen, and he immediately knew he had to have it. So, he carefully picked it up and placed it in his hoard, vowing to never let it go.\n\nBut as it turned out, the gemstone was actually a cursed object, imbued with powerful magic. And as soon as Ember touched it, he became possessed by a fierce determination to never give up or give in. He became so stubborn that he refused to listen to anyone or do anything that didn't align with his own desires.\n\nAt first, his family and friends found his newfound perseverance admirable. But as time went on, they began to realize that Ember's stubbornness was causing more harm than good. He refused to listen to advice or warnings, and he became increasingly isolated and difficult to be around.\n\nOne day, Ember's family had had enough. They gathered around him and explained that his determination was admirable, but that it had become a burden. They begged him to let go of the cursed gemstone and learn to find balance in his life.\n\nAt first, Ember resisted. He was convinced that he was right and that he couldn't possibly be wrong. But as he listened to his loved ones, he began to see that they were right. He realized that his stubbornness was causing him to miss out on all sorts of wonderful experiences and relationships.\n\nSo, with a heavy heart, Ember made the difficult decision to let go of the cursed gemstone. It was a hard choice, but he knew it was the right one. And as he let go, he felt a weight lift off his shoulders.\n\nFrom that day on, Ember learned to be determined and persevering, but also to be open-minded and willing to listen to others. He became a well-respected and much-loved member of his community, and he lived a long, happy life filled with adventure and connection.\n\nThe end. How was that?"
  },
  "s0038u0002": {
    "source_uid": "s0038u0002",
    "source_id": 189,
    "window_source_id": 9,
    "session_id": "sharegpt_xLjgprT_0",
    "session_index": 38,
    "session_local_user_index": 2,
    "timestamp": "2023-05-21T22:56:01",
    "assistant_reply": "There seem to be several different subjects with the phrase \"not bad\" in the provided search results. Here are brief explanations of each:\n\n[1] \"Not bad\" can be used as an idiom to mean \"not terrible\" or \"better than expected.\" Some synonyms for this usage of \"not bad\" might include \"not be a barrel of laughs\" (not particularly enjoyable), \"not be a bed of roses\" (not easy or pleasant), or \"not be a patch on something\" (not as good as something else).\n\n[2] \"Not bad\" can also be used more literally to mean \"adequate\" or \"acceptable.\" Some synonyms for this usage of \"not bad\" might include \"fair,\" \"decent,\" \"tolerable,\" \"average,\" \"reasonable,\" or \"moderate.\"\n\n[3] \"Bad\" can be used as an adjective to mean \"failing to reach an acceptable standard.\" In this context, \"not bad\" would mean \"not failing to reach an acceptable standard,\" or \"satisfactory.\"\n\nIt's worth noting that the phrase \"not bad\" can sometimes be used somewhat sarcastically to mean the opposite of what it literally says. For example, someone might say \"That meal was not bad\" to mean \"That meal was actually terrible,\" depending on the context and tone of voice."
  },
  "s0039u0001": {
    "source_uid": "s0039u0001",
    "source_id": 190,
    "window_source_id": 10,
    "session_id": "sharegpt_NUyiNZE_0",
    "session_index": 39,
    "session_local_user_index": 1,
    "timestamp": "2023-05-22T11:43:00.500000",
    "assistant_reply": "There are several experimental treatment options for diabetes and chronic kidney disease that are currently being studied in clinical trials. These may include new medications, new drug combinations, and new approaches to therapy such as stem cell therapy and gene therapy. For example, there are several investigational drugs that are being studied for their potential to slow the progression of kidney disease in people with diabetes. Additionally, researchers are exploring new ways to use existing medications, such as using GLP-1 receptor agonists to protect the kidneys.\n\nIt is also important to note that some of these experimental treatments may not be widely available or covered by insurance. It would be best for this individual to discuss with their healthcare provider about participating in clinical trials that may be appropriate for their condition."
  },
  "s0040u0001": {
    "source_uid": "s0040u0001",
    "source_id": 191,
    "window_source_id": 11,
    "session_id": "sharegpt_lRGmxQF_0",
    "session_index": 40,
    "session_local_user_index": 1,
    "timestamp": "2023-05-22T15:24:00.500000",
    "assistant_reply": "Night Boat to Tangier is a novel that explores a range of philosophical and metaphysical ideas. The novel, written by Kevin Barry, follows two aging Irish gangsters, Maurice Hearne and Charlie Redmond, as they wait for a boat to the Spanish city of Tangier in the hope of finding Maurice's missing daughter.\n\nOne of the central ideas of the novel is that of sin. Maurice and Charlie are both former criminals, and their lives are defined by the sins they have committed in the past. Their criminal activities have left them both with a sense of guilt and remorse, and they are haunted by the consequences of their actions. For example, Maurice's missing daughter is a direct result of his criminal lifestyle.\n\nAnother idea that is explored in the novel is that of fate. Maurice and Charlie are both trapped by the choices they have made in the past, and they are unable to escape the consequences of those choices. Their lives are defined by their past actions, and they are unable to change their fate. This sense of inevitability is emphasized by the fact that they are waiting for a boat that may never arrive, symbolizing their inability to escape their past.\n\nThe novel also explores the idea of tragedy. The lives of Maurice and Charlie are marked by a series of tragic events, from the loss of their loved ones to the failure of their criminal enterprises. These tragedies have left them both emotionally scarred, and they struggle to come to terms with their past. The novel ends with a sense of tragedy, as Maurice and Charlie are unable to find Maurice's daughter, and they are left alone to face their own mortality.\n\nAt the same time, the novel also touches on the idea of redemption. Despite their criminal past, Maurice and Charlie are both seeking redemption for their sins. They are trying to make amends for their past actions, and they are looking for a way to start over. However, their attempts at redemption are ultimately unsuccessful, as they are unable to escape the consequences of their actions.\n\nIn addition to these ideas, the novel also explores the concept of hope. Despite the hardships and tragedies they face, Maurice and Charlie are able to hold onto hope. They believe that they will eventually find Maurice's daughter, and that their lives will improve. However, this hope is ultimately proven to be false, as they are unable to find Maurice's daughter and they are left to face their own mortality.\n\nThe novel also touches on the idea of failure. Maurice and Charlie are both failures in many ways. They have failed as criminals, as fathers, and as men. Their failures have left them with a sense of despair and hopelessness, and they are unable to overcome their past mistakes.\n\nFinally, the novel explores the concept of existentialism. Maurice and Charlie are both deeply aware of their own mortality, and they are forced to confront the meaninglessness of their own lives. They are unable to find any sense of purpose or direction, and they are left to face the void of their own existence.\n\nOverall, Night Boat to Tangier is a novel that explores a range of philosophical and metaphysical ideas. From the concept of sin and fate to the ideas of tragedy, redemption, hope, and existentialism, the novel offers a complex and thought-provoking exploration of the human condition."
  },
  "s0041u0001": {
    "source_uid": "s0041u0001",
    "source_id": 192,
    "window_source_id": 12,
    "session_id": "4cbe4e20_1",
    "session_index": 41,
    "session_local_user_index": 1,
    "timestamp": "2023-05-22T09:07:00.500000",
    "assistant_reply": "Congratulations on completing the bookshelf assembly project! That's a great accomplishment!\n\nNow, let's get to the fun part - decorating your new bookshelf! Since it's a focal point in the room, you'll want to choose decorative items that complement your personal style, the room's aesthetic, and the shelf's design. Here are some popular and versatile ideas to get you started:\n\n1. **Vases and Urns**: Fill them with fresh flowers, branches, or greens to add a touch of nature and color. You can also use them as bookends or solo decorative pieces.\n2. **Decorative Boxes and Containers**: Use them to store small items like books, knick-knacks, or treasures. They can add a pop of color and texture to the shelf.\n3. **Artwork and Prints**: Hang framed art, prints, or posters that resonate with your personal style or match your room's color scheme.\n4. **Sculptures and Figurines**: Add a touch of elegance with sculptures, figurines, or collectible items that reflect your interests or hobbies.\n5. **Candles and Lanterns**: Place candles or lanterns on the shelf to create a warm, cozy ambiance. You can also use them to add a pop of color or texture.\n6. **Book-themed Decor**: Since it's a bookshelf, why not incorporate book-themed decor? Look for book-shaped decorative items, bookends, or literary-inspired art.\n7. **Personal Mementos**: Display personal items like family photos, heirlooms, or sentimental trinkets to make the bookshelf feel more personal and unique.\n8. **Greenery**: Add some potted plants or a vase with fresh greens to bring in a touch of nature and freshness.\n9. **Textiles**: Use throw blankets, scarves, or fabric pieces to add color, texture, and coziness to the shelf.\n10. **Collectibles**: Showcase your favorite collectibles, such as vintage items, figurines, or memorabilia, to add personality to the shelf.\n\nRemember to balance the items on the shelf to create visual harmony. You can group similar items together or create a mix of textures, colors, and shapes to keep the display interesting.\n\nLastly, don't forget to have fun and experiment with different arrangements until you find a look that makes you happy!"
  },
  "s0041u0002": {
    "source_uid": "s0041u0002",
    "source_id": 193,
    "window_source_id": 13,
    "session_id": "4cbe4e20_1",
    "session_index": 41,
    "session_local_user_index": 2,
    "timestamp": "2023-05-22T09:07:01",
    "assistant_reply": "For a modern and minimalist aesthetic, you'll want vases and urns that feature clean lines, simple shapes, and a limited color palette. Here are some specific styles that would fit well:\n\n1. **Simple Glass Vases**: Look for clear or frosted glass vases with a cylindrical, spherical, or rectangular shape. These will add a touch of elegance without drawing attention away from the books or other decorative items.\n2. **Ceramic or Porcelain Urns**: Opt for white, black, or gray ceramic or porcelain urns with a simple, geometric shape. These will add a subtle, sophisticated touch to your bookshelf.\n3. **Marble or Stone Vases**: Marble, travertine, or stone vases with a minimalist design will bring a touch of luxury and sophistication to your bookshelf. Look for simple shapes and a monochromatic color palette.\n4. **Industrial-Chic Vases**: Exposed concrete, metal, or reclaimed wood vases with a distressed finish can add a touch of industrial chic to your modern bookshelf.\n5. **Geometric Vases**: Vases with geometric shapes, such as triangular, hexagonal, or octagonal shapes, can add visual interest to your bookshelf. Look for simple, monochromatic designs to maintain a minimalist aesthetic.\n6. **Hanging Vases**: Suspended vases or terrariums can add a touch of modernity to your bookshelf. Look for simple, delicate designs that won't overwhelm the space.\n\nSome popular brands and designers that offer modern and minimalist vases and urns include:\n\n* Muuto\n* Ferm Living\n* HAY\n* Menu\n* Tom Dixon\n* Jonathan Adler\n* West Elm\n* CB2\n\nWhen choosing a vase or urn, consider the following:\n\n* Scale: Ensure the vase or urn is proportional to the bookshelf and the items you plan to display.\n* Material: Glass, ceramic, porcelain, marble, and stone are popular materials for modern and minimalist designs.\n* Color: Stick to a monochromatic palette or a limited color scheme to maintain a cohesive look.\n* Shape: Simple, geometric shapes will complement a modern and minimalist aesthetic.\n\nRemember, the goal is to create a clean, uncluttered look that allows the books and other decorative items to take center stage."
  },
  "s0041u0003": {
    "source_uid": "s0041u0003",
    "source_id": 194,
    "window_source_id": 14,
    "session_id": "4cbe4e20_1",
    "session_index": 41,
    "session_local_user_index": 3,
    "timestamp": "2023-05-22T09:07:01.500000",
    "assistant_reply": "A distressed metal vase can be a great addition to a modern and minimalist space, but it's essential to consider a few things to ensure it fits with the aesthetic.\n\n**Why it could work:**\n\n1. **Contrast**: A distressed metal vase can add a beautiful contrast to a modern and minimalist space, which often features clean lines, smooth surfaces, and a limited color palette. The rough, industrial texture and worn look of the vase can create a interesting visual tension.\n2. **Industrial chic**: As you mentioned, industrial-chic decor is a great way to add character to a modern space. A distressed metal vase can fit perfectly into this aesthetic, especially if you're incorporating other industrial elements, like reclaimed wood or metal accents.\n3. **Unique focal point**: A distressed metal vase can become a unique focal point in your bookshelf, drawing attention to itself without overwhelming the space.\n\n**Why it might not work:**\n\n1. **Overpowering the space**: If the vase is too large, bold, or ornate, it might overpower the minimalist aesthetic and create a sense of clutter.\n2. **Clashing styles**: If the distressed metal vase is too rustic or vintage, it might clash with the modern and minimalist style of the bookshelf and surrounding decor.\n\n**Tips to make it work:**\n\n1. **Choose a simple shape**: Opt for a vase with a simple, geometric shape, like a cylinder or a rectangular prism, to ensure it doesn't overwhelm the space.\n2. **Keep the scale in check**: Select a vase that's proportional to the bookshelf and the items you plan to display. A smaller vase can be a great way to add a touch of industrial chic without overwhelming the space.\n3. **Balance with clean lines**: Pair the distressed metal vase with clean-lined, minimalist decorative items, like a simple candle or a few carefully placed books, to create balance and harmony.\n4. **Consider a more subtle distressing**: If you're concerned about the vase being too bold, look for one with a more subtle distressing, like a gentle patina or a soft, brushed metal finish.\n\nBy following these tips, you can incorporate a distressed metal vase into your modern and minimalist bookshelf, adding a unique touch of industrial chic to the space."
  },
  "s0041u0004": {
    "source_uid": "s0041u0004",
    "source_id": 195,
    "window_source_id": 15,
    "session_id": "4cbe4e20_1",
    "session_index": 41,
    "session_local_user_index": 4,
    "timestamp": "2023-05-22T09:07:02",
    "assistant_reply": "Throw pillows are a fantastic way to add a pop of color, texture, and style to your space. For an industrial-chic vibe, you'll want pillow covers that complement the distressed metal vase and the modern, minimalist aesthetic of your bookshelf. Here are some recommendations:\n\n1. **Raw Linen or Cotton**: Opt for pillow covers made from natural materials like linen or cotton in their raw, undyed state. This will add a tactile, organic feel to your space and complement the industrial-chic vibe.\n2. **Monochromatic Neutrals**: Choose pillow covers in monochromatic neutral shades like gray, beige, taupe, or navy blue. These colors will blend seamlessly with the distressed metal vase and the minimalist aesthetic.\n3. **Textured Fabrics**: Look for pillow covers with textured fabrics like woven linen, cable knit, or bouclé. These will add depth and visual interest to your space.\n4. **Utility-Inspired Prints**: Consider pillow covers with utility-inspired prints like grid patterns, geometric shapes, or subtle industrial motifs. These will tie in nicely with the industrial-chic vibe of the distressed metal vase.\n5. **Faux Leather or Suede**: If you want to add a touch of edginess, consider pillow covers made from faux leather or suede. These will add a rugged, industrial feel to your space.\n\nSome popular brands and designers that offer industrial-chic-inspired pillow covers include:\n\n* Ferm Living\n* HAY\n* Menu\n* Muuto\n* Urban Outfitters (for a more affordable option)\n\nWhen selecting pillow covers, remember to consider the following:\n\n* **Scale**: Ensure the pillow covers are proportional to your couch and the room.\n* **Color**: Stick to a limited color palette to maintain a cohesive look.\n* **Texture**: Mix and match different textures to add depth and visual interest.\n* **Pattern**: Balance bold patterns with solid-colored pillow covers to avoid overwhelming the space.\n\nBy incorporating these elements, you'll create a cohesive, industrial-chic look that ties in perfectly with your distressed metal vase and modern, minimalist bookshelf."
  }
}