[
  {
    "answer": "Cannot be determined from the conversation.",
    "answerable": false,
    "support_memory_ids": [],
    "support_source_ids": [],
    "required_slots": [],
    "unfilled_slots": [],
    "operation": "none",
    "calculation": {
      "operator": "none",
      "operands": [],
      "unit": "",
      "result": ""
    },
    "confidence": 0.0,
    "reasoning_summary": "The only plant acquisition mentioned within the last month (2023-04-30 to 2023-05-30) is a snake plant received from the user's sister, but the memory does not specify whether it was acquired in the last month or earlier. No other acquisitions are confirmed within the time window."
  },
  {
    "answer": "Cannot be determined from the conversation.",
    "answerable": false,
    "support_memory_ids": [],
    "support_source_ids": [],
    "required_slots": [],
    "unfilled_slots": [],
    "operation": "none",
    "calculation": {
      "operator": "none",
      "operands": [],
      "unit": "",
      "result": ""
    },
    "confidence": 0.0,
    "reasoning_summary": "The only plant acquisition mentioned within the last month (2023-04-30 to 2023-05-30) is a snake plant received from the user's sister, but the memory does not specify the exact date, only 'last month' relative to May 25, 2023. Additionally, a peace lily and succulent were bought two weeks before May 20, 2023, which falls within the period. However, the question asks for a count of plants acquired, and there is no explicit statement that these are the only acquisitions. Without a complete list, the count cannot be determined."
  }
]