[
  {
    "memory_id": "m_21cf2731d71ad389e3ac",
    "content": "User wants more power and a deeper sound from their car's exhaust.",
    "state_key": "",
    "state_value": "",
    "state_status": "unknown",
    "preference": {
      "target": "exhaust sound and power",
      "polarity": "positive",
      "strength": 0.8,
      "scope": "contextual"
    },
    "relation": {
      "subject": "User",
      "predicate": "desires",
      "object": "more power and deeper sound from exhaust"
    },
    "modality": "asserted",
    "time": {
      "event_start": "",
      "event_end": "",
      "valid_from": "",
      "valid_to": "",
      "precision": "unknown",
      "raw": ""
    },
    "provenance": {
      "session_id": "84a0af4f",
      "session_index": 18,
      "source_ids": [
        94
      ],
      "source_uids": [
        "s0018u0002"
      ],
      "source_times": [
        "2023-05-23T17:39:01"
      ],
      "source_role": "user",
      "window_index": 7
    }
  },
  {
    "memory_id": "m_446fe479bbc9f19c44dd",
    "content": "User finds it interesting how performance art involves many mediums and elements, and would like to see pieces in person.",
    "state_key": "",
    "state_value": "",
    "state_status": "unknown",
    "preference": {
      "target": "live performance art",
      "polarity": "positive",
      "strength": 0.0,
      "scope": "general"
    },
    "relation": {
      "subject": "user",
      "predicate": "appreciation_for",
      "object": "multi-medium performance art"
    },
    "modality": "asserted",
    "time": {
      "event_start": "",
      "event_end": "",
      "valid_from": "2023-05-30T07:33:02.500000",
      "valid_to": "",
      "precision": "datetime",
      "raw": ""
    },
    "provenance": {
      "session_id": "ultrachat_453314",
      "session_index": 41,
      "source_ids": [
        229
      ],
      "source_uids": [
        "s0041u0005"
      ],
      "source_times": [
        "2023-05-30T07:33:02.500000"
      ],
      "source_role": "user",
      "window_index": 18
    }
  },
  {
    "memory_id": "m_449c9044524f5dc068fe",
    "content": "User thinks a spreadsheet is the most convenient way to keep track of family reunion invitees.",
    "state_key": "",
    "state_value": "",
    "state_status": "unknown",
    "preference": {
      "target": "spreadsheet for tracking invitees",
      "polarity": "positive",
      "strength": 0.7,
      "scope": "contextual"
    },
    "relation": {
      "subject": "user",
      "predicate": "prefers",
      "object": "spreadsheet for tracking invitees"
    },
    "modality": "asserted",
    "time": {
      "event_start": "",
      "event_end": "",
      "valid_from": "",
      "valid_to": "",
      "precision": "unknown",
      "raw": ""
    },
    "provenance": {
      "session_id": "43b53ac4_1",
      "session_index": 16,
      "source_ids": [
        81
      ],
      "source_uids": [
        "s0016u0002"
      ],
      "source_times": [
        "2023-05-23T16:50:01"
      ],
      "source_role": "user",
      "window_index": 6
    }
  },
  {
    "memory_id": "m_4c7ce75e2000e9117c68",
    "content": "User likes the idea of volunteering to contribute to conservation efforts during their trip.",
    "state_key": "user.preference.volunteering",
    "state_value": "positive",
    "state_status": "active",
    "preference": {
      "target": "volunteering for conservation",
      "polarity": "positive",
      "strength": 0.7,
      "scope": "contextual"
    },
    "relation": {
      "subject": "user",
      "predicate": "likes idea of",
      "object": "volunteering for conservation"
    },
    "modality": "asserted",
    "time": {
      "event_start": "",
      "event_end": "",
      "valid_from": "",
      "valid_to": "",
      "precision": "unknown",
      "raw": ""
    },
    "provenance": {
      "session_id": "ultrachat_399348",
      "session_index": 12,
      "source_ids": [
        65
      ],
      "source_uids": [
        "s0012u0004"
      ],
      "source_times": [
        "2023-05-22T18:27:02"
      ],
      "source_role": "user",
      "window_index": 5
    }
  },
  {
    "memory_id": "m_70721e09737fc5749e51",
    "content": "User is interested in Akrapovič exhaust systems for their modified Honda Civic.",
    "state_key": "",
    "state_value": "",
    "state_status": "unknown",
    "preference": {
      "target": "Akrapovič exhaust systems",
      "polarity": "positive",
      "strength": 0.7,
      "scope": "contextual"
    },
    "relation": {
      "subject": "User",
      "predicate": "interested in",
      "object": "Akrapovič exhaust systems"
    },
    "modality": "asserted",
    "time": {
      "event_start": "",
      "event_end": "",
      "valid_from": "",
      "valid_to": "",
      "precision": "unknown",
      "raw": ""
    },
    "provenance": {
      "session_id": "84a0af4f",
      "session_index": 18,
      "source_ids": [
        94
      ],
      "source_uids": [
        "s0018u0002"
      ],
      "source_times": [
        "2023-05-23T17:39:01"
      ],
      "source_role": "user",
      "window_index": 7
    }
  },
  {
    "memory_id": "m_8b30ebc5236246ccf76f",
    "content": "User likes the song 'Hasa Diga Eebowai' from The Book of Mormon for its catchy melody and humor about cultural differences.",
    "state_key": "",
    "state_value": "",
    "state_status": "unknown",
    "preference": {
      "target": "Hasa Diga Eebowai",
      "polarity": "positive",
      "strength": 0.8,
      "scope": "specific"
    },
    "relation": {
      "subject": "user",
      "predicate": "likes",
      "object": "Hasa Diga Eebowai"
    },
    "modality": "asserted",
    "time": {
      "event_start": "",
      "event_end": "",
      "valid_from": "",
      "valid_to": "",
      "precision": "unknown",
      "raw": ""
    },
    "provenance": {
      "session_id": "65162409_3",
      "session_index": 26,
      "source_ids": [
        145
      ],
      "source_uids": [
        "s0026u0006"
      ],
      "source_times": [
        "2023-05-25T08:37:03"
      ],
      "source_role": "user",
      "window_index": 11
    }
  },
  {
    "memory_id": "m_a6fc13973fd5d2e261c9",
    "content": "User has been loving overnight oats and wants to mix up breakfast options.",
    "state_key": "user.diet.breakfast_preference",
    "state_value": "overnight oats, but wants variety",
    "state_status": "active",
    "preference": {
      "target": "overnight oats",
      "polarity": "positive",
      "strength": 0.7,
      "scope": "contextual"
    },
    "relation": {
      "subject": "user",
      "predicate": "likes",
      "object": "overnight oats"
    },
    "modality": "asserted",
    "time": {
      "event_start": "",
      "event_end": "",
      "valid_from": "",
      "valid_to": "",
      "precision": "unknown",
      "raw": ""
    },
    "provenance": {
      "session_id": "ca929779_1",
      "session_index": 35,
      "source_ids": [
        191
      ],
      "source_uids": [
        "s0035u0003"
      ],
      "source_times": [
        "2023-05-27T05:41:01.500000"
      ],
      "source_role": "user",
      "window_index": 15
    }
  },
  {
    "memory_id": "m_d3cdb31023b8c7ead0f7",
    "content": "User is looking for recommendations for indie folk artists similar to Bon Iver.",
    "state_key": "",
    "state_value": "",
    "state_status": "unknown",
    "preference": {
      "target": "indie folk music similar to Bon Iver",
      "polarity": "positive",
      "strength": 0.7,
      "scope": "contextual"
    },
    "relation": {
      "subject": "user",
      "predicate": "seeking recommendations for",
      "object": "indie folk artists similar to Bon Iver"
    },
    "modality": "asserted",
    "time": {
      "event_start": "",
      "event_end": "",
      "valid_from": "",
      "valid_to": "",
      "precision": "unknown",
      "raw": ""
    },
    "provenance": {
      "session_id": "d70b7418",
      "session_index": 27,
      "source_ids": [
        146
      ],
      "source_uids": [
        "s0027u0001"
      ],
      "source_times": [
        "2023-05-25T11:02:00.500000"
      ],
      "source_role": "user",
      "window_index": 11
    }
  },
  {
    "memory_id": "m_d8f05bdecc971b416241",
    "content": "User is looking for online resources or platforms to watch documentaries and independent films conveniently with a good selection.",
    "state_key": "",
    "state_value": "",
    "state_status": "unknown",
    "preference": {
      "target": "convenient and accessible platform with good selection",
      "polarity": "positive",
      "strength": 0.7,
      "scope": "contextual"
    },
    "relation": {
      "subject": "User",
      "predicate": "seeking",
      "object": "online platforms for documentaries and independent films"
    },
    "modality": "asserted",
    "time": {
      "event_start": "",
      "event_end": "",
      "valid_from": "",
      "valid_to": "",
      "precision": "unknown",
      "raw": ""
    },
    "provenance": {
      "session_id": "78966c29_3",
      "session_index": 10,
      "source_ids": [
        55
      ],
      "source_uids": [
        "s0010u0006"
      ],
      "source_times": [
        "2023-05-22T14:08:03"
      ],
      "source_role": "user",
      "window_index": 4
    }
  },
  {
    "memory_id": "m_3b855ce9114723b1ca6c",
    "content": "User likes the song 'You and Me (But Mostly Me)' from The Book of Mormon, finding it hilarious and relatable.",
    "state_key": "",
    "state_value": "",
    "state_status": "unknown",
    "preference": {
      "target": "You and Me (But Mostly Me)",
      "polarity": "positive",
      "strength": 0.8,
      "scope": "specific"
    },
    "relation": {
      "subject": "user",
      "predicate": "likes",
      "object": "You and Me (But Mostly Me)"
    },
    "modality": "asserted",
    "time": {
      "event_start": "",
      "event_end": "",
      "valid_from": "",
      "valid_to": "",
      "precision": "unknown",
      "raw": ""
    },
    "provenance": {
      "session_id": "65162409_3",
      "session_index": 26,
      "source_ids": [
        145
      ],
      "source_uids": [
        "s0026u0006"
      ],
      "source_times": [
        "2023-05-25T08:37:03"
      ],
      "source_role": "user",
      "window_index": 11
    }
  },
  {
    "memory_id": "m_4962d3321c82945745a4",
    "content": "User expressed interest in adding several Mexican festivals to their bucket list.",
    "state_key": "user.travel_interests",
    "state_value": "Mexican festivals",
    "state_status": "active",
    "preference": {
      "target": "Mexican festivals",
      "polarity": "positive",
      "strength": 0.8,
      "scope": "general"
    },
    "relation": {
      "subject": "user",
      "predicate": "has interest in",
      "object": "Mexican festivals"
    },
    "modality": "asserted",
    "time": {
      "event_start": "",
      "event_end": "",
      "valid_from": "2023-05-28T20:38:03",
      "valid_to": "",
      "precision": "datetime",
      "raw": "2023-05-28T20:38:03"
    },
    "provenance": {
      "session_id": "ultrachat_373194",
      "session_index": 38,
      "source_ids": [
        212
      ],
      "source_uids": [
        "s0038u0006"
      ],
      "source_times": [
        "2023-05-28T20:38:03"
      ],
      "source_role": "user",
      "window_index": 17
    }
  },
  {
    "memory_id": "m_4ee205c4ce30b20d2a8a",
    "content": "User is interested in non-dairy yogurt alternatives using different types of milk.",
    "state_key": "",
    "state_value": "",
    "state_status": "unknown",
    "preference": {
      "target": "non-dairy yogurt alternatives",
      "polarity": "positive",
      "strength": 0.7,
      "scope": "contextual"
    },
    "relation": {
      "subject": "user",
      "predicate": "interested in",
      "object": "non-dairy yogurt alternatives"
    },
    "modality": "asserted",
    "time": {
      "event_start": "",
      "event_end": "",
      "valid_from": "2023-05-22T05:54:03",
      "valid_to": "",
      "precision": "datetime",
      "raw": ""
    },
    "provenance": {
      "session_id": "answer_8549e5e0",
      "session_index": 8,
      "source_ids": [
        42
      ],
      "source_uids": [
        "s0008u0006"
      ],
      "source_times": [
        "2023-05-22T05:54:03"
      ],
      "source_role": "user",
      "window_index": 3
    }
  }
]