{
  "memory_count": 200,
  "node_count": 940,
  "edge_count": 1802,
  "node_types": {
    "entity": 117,
    "location": 22,
    "memory": 200,
    "preference": 24,
    "relation_entity": 208,
    "session": 36,
    "state": 76,
    "time": 111,
    "topic": 146
  },
  "edge_types": {
    "ABOUT_ENTITY": 192,
    "ASSERTS_STATE": 80,
    "AT_LOCATION": 28,
    "BEFORE": 164,
    "EVENT_END": 7,
    "EVENT_START": 71,
    "HAS_TOPIC": 200,
    "IN_SESSION": 200,
    "NEXT_IN_SESSION": 164,
    "PREFERENCE_ABOUT": 25,
    "RELATION": 197,
    "RELATION_OBJECT": 199,
    "RELATION_SUBJECT": 199,
    "SAME_EVENT": 28,
    "SUPERSEDES": 3,
    "SUPPORTS": 1,
    "VALID_FROM": 43,
    "VALID_TO": 1
  },
  "index_cardinality": {
    "entity": 117,
    "topic": 146,
    "location": 22,
    "session": 36,
    "state_key": 76,
    "keyword": 610,
    "memory_type": 3,
    "date": 111,
    "relation_subject": 12,
    "relation_object": 197,
    "preference_target": 24
  }
}