{
  "s0004u0004": {
    "source_uid": "s0004u0004",
    "source_id": 25,
    "window_source_id": 1,
    "session_id": "5c05a50c",
    "session_index": 4,
    "session_local_user_index": 4,
    "timestamp": "2023-05-22T01:10:02",
    "assistant_reply": "Luxury shopping is a great way to treat yourself! Saks Fifth Avenue is an iconic department store with an impressive loyalty program. I'd be happy to help you understand their rewards and loyalty program.\n\n**Saks Fifth Avenue's Loyalty Program: SaksFirst**\n\nSaksFirst is Saks Fifth Avenue's loyalty program, designed to reward customers for their purchases and loyalty. Here's a breakdown of the program:\n\n1. **Earning Points:** For every dollar you spend at Saks Fifth Avenue, you'll earn 2 points. You can earn points on purchases made in-store, online, or through their mobile app.\n2. **Rewards Tiers:** There are three tiers to the SaksFirst program:\n\t* **SaksFirst:** 0-999 points (entry-level tier)\n\t* **SaksFirst Premier:** 1,000-4,999 points (mid-tier)\n\t* **SaksFirst Elite:** 5,000+ points (top-tier)\n3. **Rewards and Benefits:** Depending on your tier, you can enjoy benefits like:\n\t+ Points redemption for gift cards or merchandise\n\t+ Exclusive access to sales and early access to new arrivals\n\t+ Complimentary shipping and gift wrapping\n\t+ Special perks like personalized styling services and invitations to events\n4. **Points Expiration:** Points expire 12 months after they're earned, so be sure to use them within a year.\n\nAs you've recently purchased an Alexander McQueen blouse, you've likely earned points towards your SaksFirst account. You can check your points balance and redeem rewards by logging into your account on the Saks Fifth Avenue website or mobile app.\n\n**Other Luxury Department Store Loyalty Programs**\n\nIf you're interested in exploring other luxury department store loyalty programs, here are a few notable ones:\n\n1. **Nordstrom's The Nordy Club:** Nordstrom's loyalty program offers points for purchases, with rewards like free shipping, alterations, and exclusive access to sales.\n2. **Neiman Marcus's InCircle:** Neiman Marcus's loyalty program rewards customers with points for purchases, with benefits like free shipping, gift wrapping, and access to exclusive events.\n3. **Barneys New York's Barneys Access:** Barneys' loyalty program offers points for purchases, with rewards like exclusive access to sales, early access to new arrivals, and personalized styling services.\n\nKeep in mind that each loyalty program has its unique benefits and rewards structure, so it's worth exploring the programs of your favorite luxury department stores.\n\nI hope this helps you make the most of your SaksFirst membership and enjoy your Alexander McQueen blouse!"
  },
  "s0004u0005": {
    "source_uid": "s0004u0005",
    "source_id": 26,
    "window_source_id": 2,
    "session_id": "5c05a50c",
    "session_index": 4,
    "session_local_user_index": 5,
    "timestamp": "2023-05-22T01:10:02.500000",
    "assistant_reply": "Gucci is a great brand! While Gucci doesn't have a traditional loyalty program like Saks Fifth Avenue's SaksFirst, they do offer a few ways to reward their loyal customers.\n\n**Gucci's Loyalty Program: Gucci Première**\n\nGucci Première is an exclusive program for Gucci's most loyal customers. It's an invitation-only program, and you'll need to meet certain purchase thresholds or be invited by a Gucci sales associate to join.\n\nAs a Gucci Première member, you can enjoy benefits like:\n\n1. **Early access to new collections:** Get exclusive access to new arrivals before they're available to the general public.\n2. **Personalized service:** Enjoy personalized styling services, including priority appointments and dedicated sales associates.\n3. **Exclusive events:** Receive invitations to private events, fashion shows, and other experiences.\n4. **Special offers:** Get access to limited-time offers, special discounts, and early access to sales.\n5. **Priority service:** Receive priority service at Gucci stores, including expedited checkout and personalized support.\n\n**Gucci's Digital Loyalty Program: Gucci Wishlists**\n\nWhile Gucci doesn't have a traditional points-based loyalty program, they do offer a digital loyalty program called Gucci Wishlists. This program allows you to create a personalized wishlist of your favorite Gucci products and receive:\n\n1. **Exclusive offers:** Get notified about special offers, discounts, and promotions on the products you love.\n2. **Early access:** Enjoy early access to new arrivals and limited-edition collections.\n3. **Personalized content:** Receive personalized content, including style advice and product recommendations, based on your preferences.\n\nAs you've recently purchased a pair of Gucci sunglasses, you might not be eligible for Gucci Première just yet. However, you can still create a Gucci account and start building your wishlist to receive exclusive offers and early access to new products.\n\n**Other Luxury Brands' Loyalty Programs**\n\nSome other luxury brands offer loyalty programs or rewards, including:\n\n1. **Louis Vuitton's LV VIP:** Louis Vuitton's loyalty program offers exclusive benefits, including early access to new collections and personalized service.\n2. **Prada's Prada Privilege:** Prada's loyalty program rewards customers with points for purchases, redeemable for exclusive benefits and rewards.\n3. **Chanel's Chanel Connects:** Chanel's loyalty program offers exclusive benefits, including early access to new collections and personalized service, for its most loyal customers.\n\nKeep in mind that each luxury brand's loyalty program is unique, and some might not have a traditional points-based system. However, they often offer exclusive benefits and rewards for their loyal customers.\n\nI hope this helps you navigate Gucci's loyalty program and enjoy your new sunglasses!"
  },
  "s0004u0006": {
    "source_uid": "s0004u0006",
    "source_id": 27,
    "window_source_id": 3,
    "session_id": "5c05a50c",
    "session_index": 4,
    "session_local_user_index": 6,
    "timestamp": "2023-05-22T01:10:03",
    "assistant_reply": "Gucci Wishlists is a great way to stay connected with the brand and receive exclusive benefits. Here's more information on how it works and what you can expect:\n\n**How Gucci Wishlists Works:**\n\n1. **Create an account:** Sign up for a Gucci account on their website or through their mobile app.\n2. **Build your wishlist:** Browse Gucci's collections and add your favorite products to your wishlist. You can add items from various categories, including clothing, handbags, shoes, accessories, and more.\n3. **Personalized content:** Based on your wishlist, you'll receive personalized content, including:\n\t* Exclusive offers and promotions on the products you love\n\t* Early access to new arrivals and limited-edition collections\n\t* Style advice and product recommendations from Gucci's experts\n\t* Behind-the-scenes content, including designer interviews and fashion shows\n4. **Exclusive benefits:** As a Gucci Wishlists member, you'll receive exclusive benefits, such as:\n\t* Early access to sales and special promotions\n\t* Complimentary shipping on online orders\n\t* Priority service at Gucci stores\n\t* Invitations to exclusive events and experiences\n\n**Exclusive Offers and Benefits:**\n\nAs a Gucci Wishlists member, you can expect to receive exclusive offers and benefits, such as:\n\n1. **Early access to new collections:** Get notified about new arrivals before they're available to the general public.\n2. **Limited-time offers:** Receive special discounts, promo codes, or bundle deals on your favorite products.\n3. **Exclusive bundles:** Get access to curated bundles featuring your favorite products at a discounted price.\n4. **Early access to sales:** Enjoy early access to sales and promotions, ensuring you don't miss out on your favorite products.\n5. **Surprise and delight:** Gucci may surprise you with special gifts or rewards, such as a complimentary accessory or a discount on your next purchase.\n\n**Tips to Make the Most of Gucci Wishlists:**\n\n1. **Keep your wishlist up-to-date:** Regularly update your wishlist to reflect your current style and preferences.\n2. **Engage with Gucci's content:** Interact with Gucci's social media, email newsletters, and website content to stay informed about new arrivals, promotions, and exclusive offers.\n3. **Use your exclusive benefits:** Take advantage of your priority service, complimentary shipping, and early access to sales to make the most of your Gucci Wishlists membership.\n\nBy joining Gucci Wishlists, you'll become part of an exclusive community that receives personalized content, early access to new collections, and exclusive benefits. Enjoy your Gucci Wishlists experience!"
  },
  "s0005u0001": {
    "source_uid": "s0005u0001",
    "source_id": 28,
    "window_source_id": 4,
    "session_id": "ultrachat_449488",
    "session_index": 5,
    "session_local_user_index": 1,
    "timestamp": "2023-05-22T02:57:00.500000",
    "assistant_reply": "The human skin acts as a protective barrier in several ways:\n\n1. Physical barrier: The skin is made up of multiple layers of cells that act as a physical barrier, protecting the body from physical damage, harmful substances, and microorganisms.\n\n2. Chemical barrier: The skin produces natural antibiotics and other chemicals that protect against harmful microorganisms.\n\n3. Temperature regulation: The skin helps regulate body temperature by controlling the flow of heat and moisture from the body.\n\n4. Sensory response: The skin contains sensory receptors that detect pain, pressure, and temperature changes, alerting the body to potential danger.\n\n5. UV protection: The skin produces melanin, a pigment that helps protect against the harmful effects of ultraviolet radiation from the sun.\n\nOverall, the skin plays a critical role in protecting the body from a wide range of physical, chemical, and biological assaults."
  },
  "s0005u0002": {
    "source_uid": "s0005u0002",
    "source_id": 29,
    "window_source_id": 5,
    "session_id": "ultrachat_449488",
    "session_index": 5,
    "session_local_user_index": 2,
    "timestamp": "2023-05-22T02:57:01",
    "assistant_reply": "Skin diseases such as eczema and psoriasis can damage the skin barrier and interfere with its protective functions. \n\nEczema, also known as Atopic Dermatitis, is a chronic condition in which the skin becomes dry, itchy, and inflamed. Scratching can cause skin damage, which can lead to increased permeability of the skin and the loss of the skin barrier function. This makes the skin more vulnerable to allergens, bacteria, and irritants, which can trigger flare-ups or infections.\n\nPsoriasis is a chronic, autoimmune disease that causes white, scaly patches to appear on the skin. These patches can become itchy or painful and can crack or bleed. In psoriasis, skin cells reproduce too rapidly and build up on the skin's surface. This can lead to the loss of the skin's barrier function and leave the skin more prone to bacterial or fungal infections.\n\nIn summary, skin conditions such as eczema and psoriasis can disrupt the skin barrier and increase the susceptibility to harmful substances, infection, and other skin problems. Managing these conditions with proper care and treatment can help restore the skin barrier and protect the skin from further damage."
  },
  "s0005u0003": {
    "source_uid": "s0005u0003",
    "source_id": 30,
    "window_source_id": 6,
    "session_id": "ultrachat_449488",
    "session_index": 5,
    "session_local_user_index": 3,
    "timestamp": "2023-05-22T02:57:01.500000",
    "assistant_reply": "Skin conditions like eczema and psoriasis are chronic and there is no permanent cure, but they can be effectively managed with treatment. Treatment can help alleviate the symptoms, reduce the frequency and severity of flare-ups, and improve the quality of life for people with these conditions. \n\nFor eczema, the goals of treatment are to reduce inflammation, relieve itching, and repair the skin barrier. Treatment options include topical medications like corticosteroids, emollient therapy, and phototherapy. In some cases, oral medications or biologics may be prescribed.\n\nFor psoriasis, treatment aims to reduce inflammation, control skin cell turnover, and alleviate symptoms. Treatment options include topical medications like corticosteroids and other creams or ointments, phototherapy, oral medications, and biologic agents.\n\nIt's important to work with a dermatologist or healthcare provider to develop an individualized treatment plan that works best for each person's specific condition and needs. With proper treatment, many people with eczema and psoriasis can effectively manage their symptoms and reduce the impact of these conditions on their daily lives."
  },
  "s0005u0004": {
    "source_uid": "s0005u0004",
    "source_id": 31,
    "window_source_id": 7,
    "session_id": "ultrachat_449488",
    "session_index": 5,
    "session_local_user_index": 4,
    "timestamp": "2023-05-22T02:57:02",
    "assistant_reply": "Yes, lifestyle changes can have a positive impact on managing symptoms of eczema and psoriasis. Here are some lifestyle changes that can help:\n\n1. Diet: Eating a healthy and balanced diet can help manage symptoms of eczema and psoriasis. Foods rich in omega-3 fatty acids (such as oily fish or flaxseeds) and antioxidants (such as fruits, vegetables, and nuts) can help reduce inflammation in the body.\n\n2. Exercise: Regular exercise can help reduce stress, which is known to trigger or exacerbate symptoms of eczema and psoriasis. Exercise also helps improve overall health and well-being.\n\n3. Avoiding triggers: Identifying and avoiding triggers that can cause flare-ups of eczema and psoriasis is an important part of management. Common triggers include stress, certain foods, alcohol, fragrances, and changes in weather.\n\n4. Proper skin care: Taking good care of the skin is important for managing symptoms of eczema and psoriasis. This includes using mild and fragrance-free cleansers, applying moisturizers, and avoiding long, hot showers or baths.\n\nWhile lifestyle changes alone may not cure eczema or psoriasis, they can complement other treatments and help manage symptoms. It is important to talk to a healthcare provider to develop an individualized treatment plan that includes lifestyle changes and other treatments."
  },
  "s0006u0001": {
    "source_uid": "s0006u0001",
    "source_id": 32,
    "window_source_id": 8,
    "session_id": "sharegpt_hamCWCF_0",
    "session_index": 6,
    "session_local_user_index": 1,
    "timestamp": "2023-05-22T06:33:00.500000",
    "assistant_reply": "That sounds like an exciting and humorous concept for a platformer game! The idea of a bald man in a suit with unique abilities and upgrades is sure to provide an engaging gameplay experience. The range of settings you've suggested for levels, from city streets to underground caves to high-tech laboratories, would provide a diverse range of challenges for players to overcome.\n\nIncorporating humor through the protagonist's bald-themed puns and one-liners would add a lighthearted and entertaining element to the game. Additionally, having the overarching goal of defeating an evil corporation that's attempting to create an army of bald super-soldiers with a powerful serum adds a sense of urgency and stakes to the game.\n\nOverall, \"Bald Fury\" has the potential to be a unique and enjoyable platformer game. Good luck with developing the concept further!"
  },
  "s0006u0002": {
    "source_uid": "s0006u0002",
    "source_id": 33,
    "window_source_id": 9,
    "session_id": "sharegpt_hamCWCF_0",
    "session_index": 6,
    "session_local_user_index": 2,
    "timestamp": "2023-05-22T06:33:01",
    "assistant_reply": "Of course! I'd be happy to help you further develop your game idea. What specific aspect of the game would you like to focus on next? Is there anything you're unsure about or need help brainstorming?"
  },
  "s0006u0003": {
    "source_uid": "s0006u0003",
    "source_id": 34,
    "window_source_id": 10,
    "session_id": "sharegpt_hamCWCF_0",
    "session_index": 6,
    "session_local_user_index": 3,
    "timestamp": "2023-05-22T06:33:01.500000",
    "assistant_reply": "There are several different types of bald-themed attacks that the protagonist could have in \"Bald Fury.\" Here are some ideas:\n\n1. Headbutt: The most basic attack, the protagonist could use his bald head to headbutt enemies, dealing damage and stunning them.\n2. Bald Blast: This attack would involve the protagonist charging up energy in his bald head and releasing a powerful blast of energy that damages enemies in its path.\n3. Reflect: The protagonist could use his shiny bald head to reflect projectiles back at enemies, allowing him to turn their attacks against them.\n4. Razor Head: The protagonist could grow sharp, razor-like hairs on his bald head that he can use to slash at enemies.\n5. Bald Shield: The protagonist could create a protective shield around himself made out of his baldness, deflecting attacks and protecting himself from damage.\n6. Spin Attack: The protagonist could spin rapidly on his bald head, creating a whirlwind that damages nearby enemies.\n7. Comb Over: The protagonist could use his baldness to his advantage by flipping over his hairless head and using his comb-over as a makeshift whip to attack enemies.\n\nThese are just a few ideas, but the possibilities are endless! You could also consider having the protagonist gain new abilities and attacks as he progresses through the game, providing a sense of progression and keeping the gameplay fresh."
  },
  "s0006u0004": {
    "source_uid": "s0006u0004",
    "source_id": 35,
    "window_source_id": 11,
    "session_id": "sharegpt_hamCWCF_0",
    "session_index": 6,
    "session_local_user_index": 4,
    "timestamp": "2023-05-22T06:33:02",
    "assistant_reply": "Here are some bald puns and one-liners that the protagonist of \"Bald Fury\" could say during the game:\n\n1. \"I'm not bald, I'm just follically challenged.\"\n2. \"My baldness is my superpower.\"\n3. \"I'm not losing hair, I'm gaining head.\"\n4. \"I've got a bald head, but a heart full of fury.\"\n5. \"I'm a member of the bald and the fearless.\"\n6. \"I don't need hair to be a hero.\"\n7. \"I may be bald, but at least I don't have split ends.\"\n8. \"I don't need a wig, I've got attitude.\"\n9. \"I'm not bald, I'm aerodynamic.\"\n10. \"My head is so shiny, it's like a disco ball!\"\n\nThese are just a few examples, but you could come up with many more bald-themed puns and one-liners to add some humor and personality to the protagonist. The key is to make them light-hearted and not take the baldness too seriously."
  },
  "s0006u0005": {
    "source_uid": "s0006u0005",
    "source_id": 36,
    "window_source_id": 12,
    "session_id": "sharegpt_hamCWCF_0",
    "session_index": 6,
    "session_local_user_index": 5,
    "timestamp": "2023-05-22T06:33:02.500000",
    "assistant_reply": "Sure, here are some more bald puns and one-liners that the protagonist of \"Bald Fury\" could say:\n\n1. \"I may be bald, but I can still headbang with the best of them!\"\n2. \"I've got a bald head, but my fists are full of fury!\"\n3. \"I'm like a cue ball - smooth, bald, and always on target.\"\n4. \"My baldness gives me an edge in battle - it's harder for enemies to get a grip!\"\n5. \"I may be bald, but I'm not lacking in brains.\"\n6. \"I've got a bald head, but I'm not afraid to get it dirty.\"\n7. \"My baldness is my trademark - they'll never forget the guy with the shiny head.\"\n8. \"I don't need hair to be a hero - my baldness is my superpower.\"\n9. \"They say baldness is a sign of wisdom - I guess that makes me the wisest guy around.\"\n10. \"I may be bald, but I'm still the boss!\"\n\nThese are just a few more ideas to add some humor and personality to the game's protagonist. Feel free to use them as inspiration and come up with your own bald-themed puns and one-liners as well."
  },
  "s0006u0006": {
    "source_uid": "s0006u0006",
    "source_id": 37,
    "window_source_id": 13,
    "session_id": "sharegpt_hamCWCF_0",
    "session_index": 6,
    "session_local_user_index": 6,
    "timestamp": "2023-05-22T06:33:03",
    "assistant_reply": "Here are some ideas for potential bosses in \"Bald Fury\":\n\n1. Mad Scientist: A crazy scientist who has invented a machine that can cause people to lose their hair, and plans to use it to create an army of bald super-soldiers.\n2. Balding Giant: A giant who has been cursed with a rapidly receding hairline, and seeks revenge on the world by causing chaos and destruction.\n3. Bald Eagle: A giant bald eagle that has been genetically modified to be extra fierce and powerful, and now threatens to take over the skies.\n4. The Hair Club for Men: A group of wealthy and powerful men who are determined to prevent anyone else from becoming bald, and will stop at nothing to maintain their own luxurious locks.\n5. The Hairpiece King: A wealthy businessman who has made his fortune selling toupees and hairpieces, and is determined to crush anyone who dares to challenge his monopoly.\n6. The Balding Beast: A monstrous creature that feeds on the hair of others, and has set its sights on the protagonist's bald head as its next meal.\n7. The Barber: A skilled barber who has turned to the dark side and now uses his clippers and razors as deadly weapons, determined to rid the world of baldness.\n8. The Wig Queen: A powerful queen who rules over a kingdom of wig-wearing subjects, and sees the protagonist's baldness as a threat to her power.\n\nThese are just a few ideas for bosses in \"Bald Fury,\" but the possibilities are endless. Each boss could have its own unique abilities and attacks, and could be set in its own unique environment with its own set of challenges for the player to overcome."
  },
  "s0007u0001": {
    "source_uid": "s0007u0001",
    "source_id": 38,
    "window_source_id": 14,
    "session_id": "answer_dcb18b9b_2",
    "session_index": 7,
    "session_local_user_index": 1,
    "timestamp": "2023-05-22T07:04:00.500000",
    "assistant_reply": "I'd be happy to help you calculate the average monthly cost of Max's supplies.\n\nTo do this, I'll need some information from you. Can you please provide the following:\n\n1. A list of the supplies you purchase for Max (e.g., food, toys, vet bills, grooming, etc.)\n2. The cost of each supply item\n3. The frequency at which you purchase each supply item (e.g., weekly, bi-weekly, monthly, quarterly, annually)\n4. The duration of time you've been tracking expenses (e.g., 3 months, 6 months, 1 year)\n\nOnce I have this information, I can help you calculate the average monthly cost of Max's supplies."
  },
  "s0007u0002": {
    "source_uid": "s0007u0002",
    "source_id": 39,
    "window_source_id": 15,
    "session_id": "answer_dcb18b9b_2",
    "session_index": 7,
    "session_local_user_index": 2,
    "timestamp": "2023-05-22T07:04:01",
    "assistant_reply": "Let's start with the grain-free kibble. How much does a month's supply of kibble cost?\n\nAnd how often do you buy the dental chews? Is it a one-time purchase or do you buy them regularly (e.g., every 2 weeks, every month)?\n\nAlso, are there any other regular or occasional expenses you've been tracking for Max, such as vet bills, toys, grooming, or anything else?"
  }
}